{
  "users": [
    {
      "userId": "xPE4389SnOp",
      "token": "98slQdVnjy2wXdvnoEQdkB3UygOHQ6TAZUfVE583aLyK0cz6ZmE5MEzkBpWmiBSRAhsoIq5GjRXlUkwiA9LUhlFkn7TBIIWlucbOtpPbf7u10ll254OdHLU9VKtj9",
      "username": "bob",
      "password": "bob",
      "avatar": "https://cdn.dribbble.com/users/5534/screenshots/14230133/media/e2f853f8232acad78bf143c32f2f3a04.jpg?compress=1&resize=400x300"
    },
    {
      "userId": "aBPiBEqEZtn",
      "token": "VQLrWWJGno6WKNjEvYM0efUcbP4siU8JScceE8poUH32hVxUOlHpMi0wWnEk811AjiaXphr5rFR9RbEi9jYaCQqxwIh2yrd1fkH7dSOdZ8NaYiAm8dqwYMyUflaHD",
      "username": "jareer",
      "password": "jareer",
      "avatar": null
    },
    {
      "userId": "5oCNd69fU7F",
      "token": "0BEh3Gb0pn4MY8AaP2J53gDTowM4JCKgWCU7v9NDHlxKGn0S1bQvzMTRtKXv9Rixrexn20dyQh1QgUZ1aH2qKCbOKWrtTihcpKZhuhRTCseP9Hrh5k5hDcQNcAv8k",
      "username": "Bob",
      "password": "Bob",
      "avatar": null
    },
    {
      "userId": "E033EmrXMTq",
      "token": "tdGsxvdzPb3gFkXfcXfDYM9tDjjOKveH0GybOgrm33mgFMx3UFkCLw58NXB9bgP4C71dveSrlmNwNUuLDLuCNhJ9ym6UyHLiqBIvna6U2cg7U83uKWuDCYbiL6dDe",
      "username": "Bob2",
      "password": "Bob",
      "avatar": null
    },
    {
      "userId": "NXo8VrXTVDM",
      "token": "L9F067h1hI2OcOcOnMBadgryKt0lAx1KXcujiunrosDL2UXmCwWaQy27CALD1YORugknSMJ3KGsVSiRqHw31PWYP7znnr3Neoi5kKskPNiWzeB2gtlwcqd6KNoHpt",
      "username": "Rigby",
      "password": "Rigby@123",
      "avatar": "https://avatars.githubusercontent.com/u/57962439?v=4"
    }
  ],
  "YEcUGQZ9nfraSZTfdND0": [],
  "G8Mvdu5tbj7897mJLqfk": [
    {
      "message": "rty",
      "owner": "Rigby"
    },
    {
      "message": "rty",
      "owner": "Rigby"
    },
    {
      "message": "yrtyrty",
      "owner": "Rigby"
    },
    {
      "message": "yr",
      "owner": "Rigby"
    },
    {
      "message": "rty"
    },
    {
      "message": "rt"
    },
    {
      "message": "rt"
    },
    {
      "message": "ty"
    },
    {
      "message": "t"
    },
    {
      "message": "f"
    },
    {
      "message": "ert",
      "owner": "bob"
    },
    {
      "message": "ert",
      "owner": "bob"
    },
    {
      "message": "ert",
      "owner": "bob"
    },
    {
      "message": "546",
      "owner": "bob"
    },
    {
      "message": "f",
      "owner": "bob"
    },
    {
      "message": "f",
      "owner": "bob"
    },
    {
      "message": "f",
      "owner": "bob"
    },
    {
      "message": "f",
      "owner": "bob"
    },
    {
      "message": "fffffffffqwqqqqqqqqqqqqq",
      "owner": "bob"
    },
    {
      "message": "erg",
      "owner": "bob"
    },
    {
      "message": "g",
      "owner": "bob"
    },
    {
      "message": "f",
      "owner": "bob"
    },
    {
      "message": "hey there",
      "owner": "bob"
    },
    {
      "message": "67",
      "owner": "bob"
    },
    {
      "message": "5",
      "owner": "bob"
    },
    {
      "message": "ty",
      "owner": "bob"
    }
  ],
  "sheedDxjYdZgeUFBKGRJ": [
    {
      "message": "ergerg",
      "owner": "bob"
    },
    {
      "message": "ergerg",
      "owner": "bob"
    }
  ],
  "wfSO1dlFHpLs4khLrVQC": [
    {
      "message": "Hey there friend!\n",
      "owner": "bob"
    }
  ],
  "UMHLyJ5JIEE7pIZ40Znv": [],
  "BWKIKEx0O98y7RinoD1T": [
    {
      "message": "ert",
      "owner": "Bob2"
    }
  ],
  "OLiPWKwbtzIkrRSTcG4T": [
    {
      "message": "ert",
      "owner": "Rigby"
    },
    {
      "message": "Welcome",
      "owner": "Rigby"
    },
    {
      "message": "kkkkkkkkkkkkkkk",
      "owner": "Rigby"
    },
    {
      "message": "kkkkkkkkkkkkkkkkkk",
      "owner": "Rigby"
    },
    {
      "message": "kkkkkkkkkkkkkkkkkkkkkkkkkkkk",
      "owner": "Rigby"
    },
    {
      "message": "kkkkkkkkkkkkkkkkkkkkkkkkkkkkkkkk",
      "owner": "Rigby"
    },
    {
      "message": "kkkkkkkkkkkkkkkkkkkkkkkkkkkkkkkkkkkkkkkkkkkk",
      "owner": "Rigby"
    },
    {
      "message": "kkkkkkkkkkkkkkkkkkkkkkkkkkkkkkkkkkkkkkkkkkkkkkkkkkkkkkk",
      "owner": "Rigby"
    },
    {
      "message": "kkkkkkkkkkkkkkkkkkkkkkkkkkkkkkkkkkkkkkkkkkkkkkkkkkkkkkkkkkkkkkkkkk",
      "owner": "Rigby"
    },
    {
      "message": "kkkkkkkkkkkkkkkkkkkkkkkkkkkkkkkkkkkkkkkkkkkkkkkkkkkkkkkkkkkkkkkkkkkkk",
      "owner": "Rigby"
    },
    {
      "message": "####",
      "owner": "Rigby"
    }
  ],
  "p5MS9YTGpuvwvZiBaheX": [
    {
      "message": "fgdfg",
      "owner": "Rigby"
    }
  ],
  "776sPJA1hZoKZKASiJOU": [
    {
      "message": "fUkcker n5gger",
      "owner": "Rigby"
    },
    {
      "message": "######",
      "owner": "Rigby"
    }
  ],
  "KzX7bWnXWHcbIrzbxALu": []
}